MANIFEST.in
README.md
setup.py
hehe/LICENSE
hehe/README.md
hehe/__init__.py
hehe/common/__init__.py
hehe/common/func.py
hehe/core/__init__.py
hehe/core/base/BaseApplication.py
hehe/core/base/BaseController.py
hehe/core/base/BaseHeHe.py
hehe/core/base/Component.py
hehe/core/base/Config.py
hehe/core/base/Dictionary.py
hehe/core/base/Request.py
hehe/core/base/Response.py
hehe/core/base/__init__.py
hehe/core/base/annotation.py
hehe/core/base/exception.py
hehe/core/console/ConsoleApplication.py
hehe/core/console/ConsoleConfig.py
hehe/core/console/ConsoleController.py
hehe/core/console/ConsoleRequest.py
hehe/core/console/ConsoleResponse.py
hehe/core/console/__init__.py
hehe/core/hconfig/__init__.py
hehe/core/hconfig/config.py
hehe/core/hconfig/utils.py
hehe/core/hconfig/parser/BaseParser.py
hehe/core/hconfig/parser/XmlParser.py
hehe/core/hconfig/parser/__init__.py
hehe/core/hcontainer/__init__.py
hehe/core/hcontainer/bean.py
hehe/core/hcontainer/utils.py
hehe/core/hcontainer/base/ClassReflection.py
hehe/core/hcontainer/base/Container.py
hehe/core/hcontainer/base/Definition.py
hehe/core/hcontainer/base/__init__.py
hehe/core/hcontainer/base/annotation.py
hehe/core/hcontainer/base/aop.py
hehe/core/hcontainer/base/proxy.py
hehe/core/hevent/__init__.py
hehe/core/hevent/event.py
hehe/core/hevent/utils.py
hehe/core/hevent/base/BaseBehavior.py
hehe/core/hevent/base/BaseEvent.py
hehe/core/hevent/base/__init__.py
hehe/core/hi18n/I18n.py
hehe/core/hi18n/__init__.py
hehe/core/hi18n/base/BaseLangPackage.py
hehe/core/hi18n/base/DefaultLangPackage.py
hehe/core/hi18n/base/__init__.py
hehe/core/hi18n/utils/CommonUtil.py
hehe/core/hi18n/utils/XmlUtil.py
hehe/core/hi18n/utils/__init__.py
hehe/core/hlogger/__init__.py
hehe/core/hlogger/logger.py
hehe/core/hlogger/utils.py
hehe/core/hmiddleware/__init__.py
hehe/core/hmiddleware/middleware.py
hehe/core/hmiddleware/utils.py
hehe/core/hmiddleware/middlewares/LoadStaticRes.py
hehe/core/hmiddleware/middlewares/__init__.py
hehey.egg-info/PKG-INFO
hehey.egg-info/SOURCES.txt
hehey.egg-info/dependency_links.txt
hehey.egg-info/top_level.txt