Metadata-Version: 2.1
Name: hehey
Version: 1.0.0
Summary: hehey是一个python web 站点工具框架
Home-page: https://gitee.com/chinahehe/hehey
Author: 13564768842
Author-email: chinabluexfw@163.com
License: UNKNOWN
Platform: UNKNOWN
